README.rst
setup.py
ottr/__init__.py
ottr/generator.py
ottr.egg-info/PKG-INFO
ottr.egg-info/SOURCES.txt
ottr.egg-info/dependency_links.txt
ottr.egg-info/not-zip-safe
ottr.egg-info/requires.txt
ottr.egg-info/top_level.txt
ottr/base/__init__.py
ottr/base/argument.py
ottr/base/base_templates.py
ottr/base/template.py
ottr/base/utils.py
ottr/parsers/__init__.py
ottr/parsers/stottr/__init__.py
ottr/parsers/stottr/lexer.py
ottr/parsers/stottr/parser.py
ottr/tpl/__init__.py
ottr/tpl/rdf.py
ottr/tpl/rdfs.py