Metadata-Version: 1.0
Name: ottr
Version: 0.0.1
Summary: Manipulate OTTR Reasonable Ontology Templates in Python
Home-page: https://github.com/Callidon/pyOTTR
Author: Thomas Minier
Author-email: thomas.minier@univ-nantes.fr
License: MIT
Keywords: rdf,owl,ottr,template,ontology,reusable
Platform: UNKNOWN
